mech_interp_toolkit/.gitkeep
mech_interp_toolkit/__init__.py
mech_interp_toolkit/activation_dict.py
mech_interp_toolkit/activation_utils.py
mech_interp_toolkit/direct_logit_attribution.py
mech_interp_toolkit/gradient_based_attribution.py
mech_interp_toolkit/linear_probes.py
mech_interp_toolkit/misc.py
mech_interp_toolkit/tokenizer.py
mech_interp_toolkit/utils.py
mech_interp_toolkit-0.1.8.dist-info/licenses/LICENSE
mech_interp_toolkit-0.1.8.dist-info/METADATA
mech_interp_toolkit-0.1.8.dist-info/WHEEL
mech_interp_toolkit-0.1.8.dist-info/top_level.txt
mech_interp_toolkit-0.1.8.dist-info/RECORD
