Metadata-Version: 2.4
Name: mech-interp-toolkit
Version: 0.1.8
Summary: Mech. Interp. utility kit
Author-email: Shantanu Darveshi <shantanu.darveshi@gmail.com>
License-Expression: MIT
Project-URL: Repository, https://github.com/SD-interp/mech_interp_toolkit/tree/main
Requires-Python: >=3.12
License-File: LICENSE
Requires-Dist: einops>=0.8.1
Requires-Dist: scikit-learn>=1.8.0
Requires-Dist: torch>=2.0.0
Requires-Dist: transformers>=4.57.3
Requires-Dist: nnsight>=0.1
Provides-Extra: dev
Requires-Dist: pytest>=8.0.0; extra == "dev"
Requires-Dist: pytest-cov>=4.1.0; extra == "dev"
Requires-Dist: mypy>=1.8.0; extra == "dev"
Requires-Dist: ruff>=0.2.0; extra == "dev"
Requires-Dist: isort>=5.13.0; extra == "dev"
Dynamic: license-file
